{
  "cate": "1",
  "date": "3æ9æ¥ 23æ58å",
  "datetime": "2019-03-09T23:58",
  "video": "/news/html/20190309/movie/k10011841641_201903100008_201903100012.html",
  "duration": 145,
  "img": "html/20190309/K10011841641_1903091914_1903091915_01_03.jpg",
  "title": "くじらに衝突か？ 高速船の80人けが 新潟 佐渡沖",
  "summary": "９日正午すぎ、新潟港から佐渡に向かっていたジェット高速船が佐渡沖で海洋生物とみられる物体に衝突し、海上保安部によりますと、80人がけがをして、このうち13人が重傷ということです。",
  "more": "９日午後０時15分ごろ、新潟市の新潟港から佐渡市の両津港に向かっていた佐渡汽船のジェット高速船が海洋生物とみられる物体に衝突してけが人が出ていると、佐渡汽船から警察や消防に通報がありました。<br /><br />海上保安部によりますと、乗客と乗組員の合わせて80人がけがをして、このうち13人が腰の骨を折るなどの重傷ということです。<br /><br />船の後方部分に15センチほどの亀裂があったほか、後部の水中翼の一部が曲がっているのが確認されたということです。<br /><br />ジェット高速船は自力で航行を続けて、予定よりおよそ１時間遅れて午後１時半ごろ、両津港に到着し、けがをした人を随時、病院に搬送したということです。<br /><br />佐渡汽船によりますと、ジェット高速船は定員250人で、この便には乗客121人と乗組員４人のあわせて125人が乗って午前11時半に新潟港を出港し、午後０時半ごろに両津港に到着する予定でした。<br /><br />警察や海上保安部などでさらに詳しい原因を調べています。",
  "body": [
    {
      "title": "乗客「すごい衝撃だった」",
      "img": "",
      "align": "",
      "text": "ジェット高速船に乗っていた男性の乗客は「すごい衝撃でした。トイレから戻るところでシートベルトをしてなかったのでびっくりしました。鼻血を出している人がいましたが、叫んだりする人はいませんでした。海洋生物にぶつかったということですが、無事に着いてよかった」と話していました。<br /><br />女性の乗客は「『ガーン』と落ちる感じでした。２階の窓側の外側の席に座っていましたが、後ろの席で腰が痛いと言っている人や鼻血を出している人がいました」と話していました。",
      "textPos": ""
    },
    {
      "title": "専門家「くじらではないか」",
      "img": "",
      "align": "",
      "text": "日本海の海洋生物に詳しい新潟県上越市にある市立水族博物館、「うみがたり」の池口新一郎副館長は「高速船に大きな衝撃を与えたとすると、クジラではないかと考えられる。日本海ではミンククジラやナガスクジラ、それにザトウクジラなどのクジラが１年を通じて回遊していて、大きいものでは20メートルほどにもなる。クジラは息を吸うために突然、水面に上がってくることもあるので、高速船ではよけようがなかったのではないか」と話していました。",
      "textPos": ""
    },
    {
      "title": "ジェット高速船 最大定員は250人",
      "img": "",
      "align": "",
      "text": "佐渡汽船のジェット高速船は昭和52年に運航をはじめました。１階と２階に座席があり、乗客の定員は最大で250人です。船体の前と後ろにある水中翼の揚力によって船体を海面から浮かせ、最高時速80キロで航行します。新潟と佐渡の間のおよそ80キロの航路をカーフェリーの半分以下の65分で結び、観光やビジネスなどに利用されています。今の時期は今回事故のあった「ぎんが」と、もう１隻の「すいせい」の合わせて２隻で、１日５往復で合わせて10便運航しています。",
      "textPos": ""
    },
    {
      "title": "平成７年 クジラ？と衝突",
      "img": "",
      "align": "",
      "text": "佐渡汽船によりますと、平成７年にも高速船がクジラとみられる海洋生物と衝突し、乗客13人がけがをする事故があったということです。<br /><br />佐渡汽船では、クジラなど海洋生物との衝突を防ぐため、「水中警報装置」と呼ばれる音の発生装置を船に取り付けて、海中にクジラが嫌がる音を出したり、見張りの担当者が船上から目視でクジラがいるかどうか確認したりしているということです。<br /><br />また、クジラが目撃された海域では、スピードを落として運航しているということです。高速船の乗客はシートベルトを着用することになっていて、佐渡汽船によりますと、出航前に船内放送で着用を呼びかけているほか、乗員が巡回して着用を確認しているということです。",
      "textPos": ""
    },
    {
      "title": "運輸安全委 調査官３人を派遣",
      "img": "",
      "align": "",
      "text": "新潟港から佐渡に向かっていたジェット高速船が佐渡沖で海洋生物とみられる物体に衝突した事故で、運輸安全委員会は９日、現地に船舶事故調査官３人を派遣しました。<br /><br />調査官は10日から高速船の損傷を調査するほか、乗組員から事情を聞くなどして事故の原因を調べることにしています。",
      "textPos": ""
    },
    {
      "title": "佐渡汽船「心より深くおわび申し上げます」",
      "img": "",
      "align": "",
      "text": "今回の事故を受けて、佐渡汽船は「本日発生した事故でご迷惑をお掛けしたお客様に、心より深くおわび申し上げます。けがをしたお客様が１日も早く快癒されるよう、誠心誠意対応してまいります。事故の原因については、現在、調査中です」とのコメントを出しました。",
      "textPos": ""
    }
  ],
  "relationNews": [
    {
      "link": "html/20190309/k10011841181000.html",
      "title": "商船三井客船 船長の“飲酒事故” の調査結果公表せず",
      "date": "3月9日  4時03分",
      "datetime": "2019-03-09T04:03",
      "imgPath": "html/20190309/K10011841181_1903082210_1903082210_01_02.jpg",
      "iconPath": "html/20190309/K10011841181_1903082210_1903082210_02_01.jpg",
      "video": "https://www3.nhk.or.jp/news/html/20190309/movie/k10011841181_201903090615_201903090616.html",
      "duration": 77
    },
    {
      "link": "html/20190308/k10011840211000.html",
      "title": "地下鉄日比谷線脱線事故から19年 遺族らが犠牲者を追悼",
      "date": "3月8日  12時40分",
      "datetime": "2019-03-08T12:40",
      "imgPath": "html/20190308/K10011840211_1903081232_1903081240_01_03.jpg",
      "iconPath": "html/20190308/K10011840211_1903081232_1903081240_02_01.jpg",
      "video": "https://www3.nhk.or.jp/news/html/20190308/movie/k10011840211_201903081232_201903081234.html",
      "duration": 65
    },
    {
      "link": "html/20190308/k10011840221000.html",
      "title": "グアム客船事故で商船三井客船に行政処分",
      "date": "3月8日  12時26分",
      "datetime": "2019-03-08T12:26",
      "imgPath": "html/20190308/K10011840221_1903081223_1903081226_01_02.jpg",
      "iconPath": "html/20190308/K10011840221_1903081223_1903081226_02_01.jpg",
      "video": "",
      "duration": 0
    },
    {
      "link": "html/20190307/k10011839431000.html",
      "title": "あおり事故「ネットのデマで被害」 書き込んだ８人を提訴 福岡",
      "date": "3月7日  19時25分",
      "datetime": "2019-03-07T19:25",
      "imgPath": "html/20190307/K10011839431_1903071938_1903071940_01_03.jpg",
      "iconPath": "html/20190307/K10011839431_1903071938_1903071940_02_01.jpg",
      "video": "https://www3.nhk.or.jp/news/html/20190307/movie/k10011839431_201903071938_201903071940.html",
      "duration": 98
    }
  ],
  "relationLink": [
    {
      "link": "http://www3.nhk.or.jp/news/html/20190102/k10011761561000.html",
      "title": "関空タンカー衝突事故 なぜ航行規制できなかった？",
      "time": "News Up 1月2日",
      "datetime": "2019-01-02"
    },
    {
      "link": "http://www3.nhk.or.jp/news/html/20181121/k10011719331000.html",
      "title": "タオルがシカに 長靴がイノシシに？",
      "time": "News Up 11月21日",
      "datetime": "2018-11-21"
    },
    {
      "link": "http://www3.nhk.or.jp/news/html/20180919/k10011635481000.html",
      "title": "命を奪うタイヤ 新たな点検義務化へ",
      "time": "News Up 9月19日",
      "datetime": "2018-09-19"
    }
  ],
  "word": [],
  "news_id": "k10011841641000",
  "yyyy": "2019",
  "mm": "03",
  "dd": "09",
  "url": "https://www3.nhk.or.jp/news/html/20190309/k10011841641000.html"
}