{
  "cate": "3",
  "date": "3æ28æ¥ 4æ14å",
  "datetime": "2019-03-28T04:14",
  "video": "/news/html/20190328/movie/k10011863371_201903280540_201903280549.html",
  "duration": 53,
  "img": "html/20190328/K10011863371_1903280540_1903280549_01_03.jpg",
  "title": "国内の二酸化炭素濃度 これまでで最も高い数値に",
  "summary": "地球温暖化の原因となる温室効果ガスの一つ、二酸化炭素の平均濃度は、去年、国内３か所にある気象庁のすべての観測点でこれまでで最も高い値になりました。",
  "more": "気候変動の監視のため、気象庁は、岩手県大船渡市三陸町綾里と沖縄県の与那国島、小笠原諸島の南鳥島の３か所で二酸化炭素濃度の観測を続けています。<br /><br />３か所の去年１年間の二酸化炭素の平均濃度は、大船渡市で412ｐｐｍ、与那国島で411.7ｐｐｍ、南鳥島で409.4ｐｐｍとなり、いずれもおととしを上回り、観測史上最高となりました。<br /><br />また、日本の南東の上空で航空機を使って行った観測や、船を使った海洋上の観測でも、観測値は最も高くなったということです。<br /><br />国連のＩＰＣＣ＝「気候変動に関する政府間パネル」は、今世紀末の気温上昇を２度未満に抑えるための目安として、二酸化炭素の濃度を世界の平均で420ｐｐｍ程度にすべきとしています。<br /><br />しかし、国内の観測点では上昇が続いていて、あと５年ほどで目安を超える可能性があります。<br /><br />気象庁は「国内の二酸化炭素の平均濃度は、観測開始以来一度も下がることなく増え続けていて、人間活動による化石燃料の消費が原因と考えられる。二酸化炭素削減の取り組みをより一層進めていく必要がある」と話しています。",
  "body": [
    {
      "title": "",
      "img": "",
      "align": "",
      "text": "",
      "textPos": ""
    }
  ],
  "relationNews": [
    {
      "link": "html/20190327/k10011862221000.html",
      "title": "去年のＣＯ２排出量 世界全体で331億トン余 過去最多",
      "date": "3月27日  7時08分",
      "datetime": "2019-03-27T07:08",
      "imgPath": "html/20190327/K10011862221_1903270906_1903270928_01_02.jpg",
      "iconPath": "html/20190327/K10011862221_1903270906_1903270928_02_01.jpg",
      "video": "",
      "duration": 0
    }
  ],
  "relationLink": [
    {
      "link": "//www3.nhk.or.jp/news/business_tokushu/2018_0828.html",
      "title": "オーストラリアの水素が日本を救う！？",
      "time": "ビジネス特集 8月28日",
      "datetime": "2018-08-28"
    },
    {
      "link": "http://www3.nhk.or.jp/news/html/20190326/k10011860791000.html",
      "title": "「ふるさとに帰りたい」 チベット動乱から60年",
      "time": "WEB特集 3月26日",
      "datetime": "2019-03-26"
    },
    {
      "link": "http://www3.nhk.or.jp/news/html/20190325/k10011859591000.html",
      "title": "サザンの“ＴＳＵＮＡＭＩ” 今 どう思いますか？",
      "time": "WEB特集 3月25日",
      "datetime": "2019-03-25"
    },
    {
      "link": "http://www3.nhk.or.jp/news/html/20190326/k10011861221000.html",
      "title": "いったい何が!? 津波浸水想定域にマイホーム",
      "time": "News Up 3月26日",
      "datetime": "2019-03-26"
    },
    {
      "link": "http://www.nhk.or.jp/kaisetsu-blog/100/317053.html",
      "title": "「急がれる代替フロン対策」（時論公論）",
      "time": "解説委員室ブログ 3月27日",
      "datetime": "2019-03-27"
    }
  ],
  "word": [
    {
      "link": "word/0000417.html",
      "title": "環境"
    }
  ],
  "news_id": "k10011863371000",
  "yyyy": "2019",
  "mm": "03",
  "dd": "28",
  "url": "https://www3.nhk.or.jp/news/html/20190328/k10011863371000.html"
}