{
  "cate": "6",
  "date": "3æ12æ¥ 5æ42å",
  "datetime": "2019-03-12T05:42",
  "video": "/news/html/20190312/movie/k10011844671_201903120950_201903120959.html",
  "duration": 130,
  "img": "html/20190312/K10011844671_1903120526_1903120542_01_02.jpg",
  "title": "エチオピア旅客機墜落 ボーイング同型機 運航停止の動きも",
  "summary": "アフリカ北東部のエチオピアで旅客機が墜落して、乗客乗員157人全員が死亡した事故で、安全性への懸念から、ほかの航空会社でも墜落したボーイングと同じ型の機体の運航を停止する動きが出ていて、波紋が広がっています。",
  "more": "この事故は、エチオピアの首都アディスアベバから隣国ケニアの首都ナイロビに向かったエチオピア航空の旅客機が10日、離陸直後に墜落し、多くの外国人を含む乗客乗員157人全員が死亡したものです。<br /><br />現地の航空当局などは、墜落した旅客機の飛行状況を記録した「フライトレコーダー」と、操縦室内の音声を記録した「ボイスレコーダー」を回収するなどして事故原因の調査を進めていますが、これまでのところ、墜落の前、パイロットが管制官との交信で、問題が生じたため、引き返すと伝えていたこと以外、詳しいことは明らかになっていません。<br /><br />こうした中、今回墜落した「ボーイング737ＭＡＸ８」と同じ型の機体が去年10月、インドネシアでも墜落し、乗客乗員189人が死亡していたことから、安全性への懸念が出ています。<br /><br />このうち、中国の航空当局は11日、２つの事故に一定の類似性があるとして、国内の航空各社に一時的に同型機の運航の停止を求める通知を出したほか、インドネシアやエチオピア、それに南アフリカでも運航を停止する動きが出ていて、波紋が広がっています。",
  "body": [
    {
      "title": "国連では半旗も",
      "img": "",
      "align": "",
      "text": "墜落した旅客機の犠牲者の中に、多くの国連機関の職員が含まれていたことを受けて、国連は、ニューヨークの国連本部に国連旗の半旗を掲げて犠牲者を追悼しました。<br /><br />国連によりますと、墜落事故で死亡した国連機関の職員は合わせて21人で、ＷＦＰ＝世界食糧計画が７人、ＵＮＨＣＲ＝国連難民高等弁務官事務所とＵＮＯＮ＝国連ナイロビ事務所がそれぞれ３人、ＩＴＵ＝国際電気通信連合が２人、このほか、世界銀行、ＦＡＯ＝国連食糧農業機関、ＩＯＭ＝国際移住機関、ＵＮＤＰ＝国連開発計画、ＵＮＥＰ＝国連環境計画、それにＵＮＳＯＭ＝国連ソマリア支援ミッションがそれぞれ１人と数多くの機関に及んでいます。<br /><br />ニューヨークの国連本部では11日、各国の政府やＮＧＯの担当者が出席して女性の地位向上について話し合う国際会議が始まり、開幕式でグテーレス事務総長は、沈痛な表情で国連職員の犠牲者に哀悼のことばを述べました。<br /><br />この中で、グテーレス事務総長は「悲劇が国連を襲い、国連は悲しみを共有している。彼らには１つの共通点があった。それは世界の人々のために働き、世界をよりよくしたいという気概だ。この重要な会議を開くにあたってこの精神を受け継ぎ、彼らをたたえよう」と述べました。",
      "textPos": ""
    },
    {
      "title": "ボーイング株は下落",
      "img": "",
      "align": "",
      "text": "今回の事故を受けて、週明け11日のニューヨーク株式市場では、今後、受注の減少など、何らかの影響は避けられないという見方から、ボーイングの株価は、先週末に比べて一時13％近く下落するなど、大きく値下がりしました。<br /><br />週明けのニューヨーク株式市場では、ボーイングの株価が取り引き開始直後に13％近く下落するなど、売り注文が集まり、結局、先週末に比べてマイナス5.4％と大きく値下がりしました。<br /><br />これは、事故を受けて、中国やインドネシアで同型機の運航を停止する動きが出ているほか、今月13日に予定していた新型機の発表も延期したことで、市場では今後、受注の減少など何らかの影響は避けられないという見方が広がったためです。<br /><br />一方、ボーイングも構成する銘柄の一つとなっているダウ平均株価は、取り引き開始直後は下落しましたが、先週まで５日続けて値下がりしていたこともあって、ボーイング以外の銘柄で買い戻す動きが強まり、11日の終値は、先週末に比べて200ドル64セント高い、２万5650ドル88セントで取り引きを終えています。",
      "textPos": ""
    },
    {
      "title": "米大統領補佐官「調査に協力」",
      "img": "",
      "align": "",
      "text": "アメリカのボルトン大統領補佐官は11日、ツイッターに文章を投稿し、「あまりに多くの命を奪った悲劇に触れ私たちは深い悲しみを感じている」として哀悼の意を示しました。そのうえで「アメリカは緊密なパートナーであるエチオピアの調査を支援している」として事故の調査に協力する考えを示しました。",
      "textPos": ""
    }
  ],
  "relationNews": [
    {
      "link": "html/20190312/k10011845111000.html",
      "title": "エチオピア旅客機墜落 米連邦航空局は同型機の運航停止求めず",
      "date": "3月12日  12時45分",
      "datetime": "2019-03-12T12:45",
      "imgPath": "html/20190312/K10011845111_1903121219_1903121245_01_02.jpg",
      "iconPath": "html/20190312/K10011845111_1903121219_1903121245_02_01.jpg",
      "video": "",
      "duration": 0
    },
    {
      "link": "html/20190311/k10011844561000.html",
      "title": "ＮＹ市場 ボーイング株価急落で始まる エチオピア航空機墜落で",
      "date": "3月11日  23時29分",
      "datetime": "2019-03-11T23:29",
      "imgPath": "html/20190311/K10011844561_1903112313_1903112329_01_02.jpg",
      "iconPath": "html/20190311/K10011844561_1903112313_1903112329_02_01.jpg",
      "video": "",
      "duration": 0
    },
    {
      "link": "html/20190311/k10011844431000.html",
      "title": "エチオピア旅客機墜落 記録装置を回収",
      "date": "3月11日  21時23分",
      "datetime": "2019-03-11T21:23",
      "imgPath": "html/20190311/K10011844431_1903112040_1903112123_01_02.jpg",
      "iconPath": "html/20190311/K10011844431_1903112040_1903112123_02_01.jpg",
      "video": "",
      "duration": 0
    },
    {
      "link": "html/20190311/k10011843171000.html",
      "title": "エチオピア旅客機墜落 157人死亡 機長は引き返そうとしていた",
      "date": "3月11日  13時46分",
      "datetime": "2019-03-11T13:46",
      "imgPath": "html/20190311/K10011843171_1903110833_1903110833_01_02.jpg",
      "iconPath": "html/20190311/K10011843171_1903110833_1903110833_02_01.jpg",
      "video": "https://www3.nhk.or.jp/news/html/20190311/movie/k10011843171_201903111105_201903111106.html",
      "duration": 56
    }
  ],
  "relationLink": [
    {
      "link": "https://www3.nhk.or.jp/news/special/international-news/breakfast/",
      "title": "朝食前のあなたに…ちょっと気になる国際ニュース",
      "time": "",
      "datetime": ""
    },
    {
      "link": "https://www3.nhk.or.jp/news/easy/k10011844671000/k10011844671000.html",
      "title": "エチオピアで落ちた飛行機と同じタイプ「安全が心配」",
      "time": "NEWSWEB EASY 3月13日",
      "datetime": "2019-03-13"
    }
  ],
  "word": [
    {
      "link": "word/0000562.html",
      "title": "国際３"
    }
  ],
  "news_id": "k10011844671000",
  "yyyy": "2019",
  "mm": "03",
  "dd": "12",
  "url": "https://www3.nhk.or.jp/news/html/20190312/k10011844671000.html"
}