{
  "cate": "1",
  "date": "3æ19æ¥ 5æ32å",
  "datetime": "2019-03-19T05:32",
  "video": "/news/html/20190319/movie/k10011852841_201903190537_201903190538.html",
  "duration": 59,
  "img": "html/20190319/K10011852841_1903190537_1903190538_01_03.jpg",
  "title": "絶滅危惧のジュゴンか １頭死んだ状態で見つかる",
  "summary": "国の天然記念物で絶滅する危険性が極めて高い、ジュゴンとみられる生物１頭が、沖縄本島北部の今帰仁村の沖合で死んでいる状態で見つかり、19日、専門家が詳しく調査することにしています。",
  "more": "18日午後５時すぎ、沖縄県今帰仁村の今帰仁漁港からおよそ200メートルの沖合で、漁業者がジュゴンのような生物が浮いているのを見つけ、陸揚げしたところ死んでいるのが確認されました。<br /><br />漁業者などによりますと、体長は３メートルほどで、三角形をした尾の特徴などから国の天然記念物のジュゴンとみられるということで、19日、専門家が詳しく調査することにしています。<br /><br />ジュゴンは暖かい海に生息し海草や藻などを餌としていて、環境省は、近い将来に絶滅する危険性が極めて高いほ乳類に指定しています。<br /><br />沖縄防衛局の調査によりますと、沖縄本島周辺では数頭しか確認されていません。<br /><br />今帰仁村漁業協同組合の與那嶺好和代表理事組合長は、「今帰仁村の周辺でたびたび泳いでいる情報を聞いたことはあるが、見るのは初めてだ」と話しています。",
  "body": [
    {
      "title": "",
      "img": "",
      "align": "",
      "text": "",
      "textPos": ""
    }
  ],
  "relationNews": [],
  "relationLink": [
    {
      "link": "http://www3.nhk.or.jp/lnews/okinawa/",
      "title": "NHK沖縄放送局",
      "time": "各地のニュース",
      "datetime": ""
    },
    {
      "link": "https://www3.nhk.or.jp/news/special/genpatsuqa/",
      "title": "原発問題 今どうなってるの？ ～だいたいわかる・語れる～",
      "time": "",
      "datetime": ""
    },
    {
      "link": "http://www3.nhk.or.jp/news/html/20190315/k10011849491000.html",
      "title": "給料ＵＰ 早くも息切れ？",
      "time": "ビジネス特集 3月15日",
      "datetime": "2019-03-15"
    },
    {
      "link": "https://www3.nhk.or.jp/news/special/heisei/interview/interview_02.html",
      "title": "森永卓郎さん「とてつもない大転落」",
      "time": "平成-次代への道標-",
      "datetime": ""
    }
  ],
  "word": [
    {
      "link": "word/0000417.html",
      "title": "環境"
    }
  ],
  "news_id": "k10011852841000",
  "yyyy": "2019",
  "mm": "03",
  "dd": "19",
  "url": "https://www3.nhk.or.jp/news/html/20190319/k10011852841000.html"
}