{
  "news_id": "k10011839721000",
  "news_prearranged_time": "2019-03-11 11:30:00",
  "title": "女性の部長や課長の割合　日本は１２％でとても低い",
  "title_with_ruby": "<ruby>女性<rt>じょせい</rt></ruby>の<ruby>部長<rt>ぶちょう</rt></ruby>や<ruby>課長<rt>かちょう</rt></ruby>の<ruby>割合<rt>わりあい</rt></ruby>　<ruby>日本<rt>にっぽん</rt></ruby>は１２％でとても<ruby>低<rt>ひく</rt></ruby>い",
  "outline_with_ruby": "<p>ＩＬＯ（<ruby>国際<rt>こくさい</rt></ruby><ruby>労働<rt>ろうどう</rt></ruby><ruby>機関<rt>きかん</rt></ruby>）によると、２０１８<ruby>年<rt>ねん</rt></ruby>、<ruby>世界<rt>せかい</rt></ruby>の<ruby>会社<rt>かいしゃ</rt></ruby>などで<ruby>働<rt>はたら</rt></ruby>く<ruby>部長<rt>ぶちょう</rt></ruby>や<ruby>課長<rt>かちょう</rt></ruby>などの<ruby>管理職<rt>かんりしょく</rt></ruby>の<ruby>中<rt>なか</rt></ruby>で、<ruby>女性<rt>じょせい</rt></ruby>の<a href='javascript:void(0)' class='dicWin' id='id-0000'><ruby>割合<rt>わりあい</rt></ruby></a>は<a href='javascript:void(0)' class='dicWin' id='id-0001'><ruby>約<rt>やく</rt></ruby></a>２７％でした。",
  "has_news_web_image": true,
  "has_news_web_movie": true,
  "has_news_easy_image": false,
  "has_news_easy_movie": false,
  "has_news_easy_voice": true,
  "news_web_image_uri": "https://www3.nhk.or.jp/news/html/20190308/../20190308/K10011839721_1903080646_1903080648_01_03.jpg",
  "news_web_movie_uri": "k10011839721_201903080646_201903080648.mp4",
  "news_easy_image_uri": "''",
  "news_easy_movie_uri": "''",
  "news_easy_voice_uri": "k10011839721000.mp4",
  "url": "http://www3.nhk.or.jp/news/easy/k10011839721000/k10011839721000.html"
}